exe2png/__init__.py
exe2png/__main__.py
exe2png-1.0.1.dist-info/LICENSE
exe2png-1.0.1.dist-info/METADATA
exe2png-1.0.1.dist-info/WHEEL
exe2png-1.0.1.dist-info/entry_points.txt
exe2png-1.0.1.dist-info/top_level.txt
exe2png-1.0.1.dist-info/RECORD
