Metadata-Version: 2.1
Name: exe2png
Version: 1.0.1
Summary: Convert executables (or any other file) into an image
Home-page: https://github.com/donno2048/exe2png
Author: Elisha Hollander
Author-email: just4now666666@gmail.com
License: MIT
Project-URL: Documentation, https://github.com/donno2048/exe2png#readme
Project-URL: Bug Reports, https://github.com/donno2048/exe2png/issues
Project-URL: Source Code, https://github.com/donno2048/exe2png
Classifier: Programming Language :: Python :: 3
Requires-Python: >=3.0
License-File: LICENSE
Requires-Dist: pillow
Requires-Dist: numpy
